[
 {
   "소방서명": "종로소방서",
   "위치": "서울특별시 종로구 종로1길 28(수송동)",
   "관할구역": "종로구 일원",
   "연락처": "730-0119",
   "위도": "37.5728109",
   "경도": "126.97912509999999"

 },
 {
   "소방서명": "중부소방서",
   "위치": "서울특별시 중구 퇴계로 394(무학동)",
   "관할구역": "중구 일원",
   "연락처": "2253-0119",
   "위도": "37.5648219",
   "경도": "127.0153596"
 },
 {
   "소방서명": "광진소방서",
   "위치": "서울특별시 광진구 광나루로 480(구의동)",
   "관할구역": "광진구 일원",
   "연락처": "446-1385",
   "위도": "37.5460406",
   "경도": "127.07932229999999"
 },
 {
   "소방서명": "용산소방서",
   "위치": "서울특별시 용산구 한강대로 167(한강로2가)",
   "관할구역": "용산구 일원",
   "연락처": "796-6361",
   "위도": "37.5310177",
   "경도": "126.9681999"
 },
 {
   "소방서명": "동대문소방서",
   "위치": "서울특별시 동대문구 장한로 34(장안동)",
   "관할구역": "동대문구 일원",
   "연락처": "2212-0199",
   "위도": "37.5638684",
   "경도": "127.06680879999999"
 },
 {
   "소방서명": "중랑소방서",
   "위치": "서울특별시 중랑구 신내로 183(신내동)",
   "관할구역": "중랑구 일원",
   "연락처": "3421-8911",
   "위도": "37.6153417",
   "경도": "127.09487070000002"
 },
 {
   "소방서명": "영등포소방서",
   "위치": "서울특별시 영등포구 문래로 197(영등포동4가)",
   "관할구역": "영등포구 일원",
   "연락처": "2679-0120",
   "위도": "37.5183994",
   "경도": "126.9041724"
 },
 {
   "소방서명": "성북소방서",
   "위치": "서울특별시 성북구 종암로 27길 3(종암동)",
   "관할구역": "성북구 일원",
   "연락처": "925-2001",
   "위도": "37.6023364",
   "경도": "127.0317849"
 },
 {
   "소방서명": "강북소방서",
   "위치": "서울특별시 강북구 보건소길 2(번동)",
   "관할구역": "강북구 일원",
   "연락처": "6946-0119",
   "위도": "37.632083400000006",
   "경도": "127.03876729999999"
 },
 {
   "소방서명": "도봉소방서",
   "위치": "서울특별시 도봉구 도봉로 666(방학동)",
   "관할구역": "도봉구 일원",
   "연락처": "3492-3438",
   "위도": "37.6640118",
   "경도": "127.0433762"
 },
 {
   "소방서명": "노원소방서",
   "위치": "서울특별시 노원구 한글비석로 1길 8(하계동)",
   "관할구역": "노원구 일원",
   "연락처": "976-6119",
   "위도": "37.638111599999995",
   "경도": "127.07108840000001"
 },
 {
   "소방서명": "은평소방서",
   "위치": "서울특별시 은평구 통일로 962(진관동)",
   "관할구역": "은평구 일원 ",
   "연락처": "389-6119",
   "위도": "37.6338132",
   "경도": "126.9117734"
 },
 {
   "소방서명": "서대문소방서",
   "위치": "서울특별시 서대문구 연희로 182(연희동)",
   "관할구역": "서대문구 일원",
   "연락처": "3141-3319",
   "위도": "37.5731167",
   "경도": "126.93600690000001"

 },
 {
   "소방서명": "마포소방서",
   "위치": "서울특별시 마포구 창전로 76(신수동)",
   "관할구역": "마포구 일원",
   "연락처": "701-3495",
   "위도": "37.5491344",
   "경도": "126.93317350000001"
 },
 {
   "소방서명": "강남소방서",
   "위치": "서울특별시 강남구 테헤란로 629(삼성동)",
   "관할구역": "강남구 일원",
   "연락처": "553-2247",
   "위도": "37.5102372",
   "경도": "127.0668095"
 },
 {
   "소방서명": "서초소방서",
   "위치": "서울특별시 서초구 사평대로 67(반포동)",
   "관할구역": "서초구 일원",
   "연락처": "591-0119",
   "위도": "37.4985816",
   "경도": "126.99195929999999"
 },
 {
   "소방서명": "관악소방서",
   "위치": "서울특별시 관악구 관악로 97(봉천동)",
   "관할구역": "관악구 일원",
   "연락처": "883-5119",
   "위도": "37.473778800000005",
   "경도": "126.95253779999997"
 },
 {
   "소방서명": "동작소방서",
   "위치": "서울특별시 동작구 여의대방로16길 55(신대방동)",
   "관할구역": "동작구 일원",
   "연락처": "848-7600",
   "위도": "37.494574",
   "경도": "126.91764309999998"
 },
 {
   "소방서명": "강서소방서",
   "위치": "서울특별시 강서구 양천로 550(등촌동)",
   "관할구역": "강서구 일원",
   "연락처": "3661-1119",
   "위도": "37.5579782",
   "경도": "126.86023129999998"
 },
 {
   "소방서명": "양천소방서",
   "위치": "서울특별시 양천구 목동서로 180(목동)",
   "관할구역": "양천구 일원",
   "연락처": "2651-7385",
   "위도": "37.5301152",
   "경도": "126.87226319999998"
 },
 {
   "소방서명": "강동소방서",
   "위치": "서울특별시 강동구 성내로 39(성내동)",
   "관할구역": "강동구 일원",
   "연락처": "483-4383",
   "위도": "37.5293802",
   "경도": "127.1251007"
 },
 {
   "소방서명": "송파소방서",
   "위치": "서울특별시 송파구 오금로51길 56(마천동)",
   "관할구역": "송파구 일원",
   "연락처": "431-4105",
   "위도": "37.4997988",
   "경도": "127.1425822"
 },
 {
   "소방서명": "구로소방서",
   "위치": "서울특별시 구로구 경인로 408(고척동)",
   "관할구역": "구로구 및 금천구 일원",
   "연락처": "2615-0119",
   "위도": "37.4981852",
   "경도": "126.8671971"
 },
 {
"소방서명": "성동소방서",
"위치": "서울특별시 성동구 살곶이길 331(행당동)",
"관할구역": "성동구 일원",
"연락처": "2622-1605",
"위도": "37.553978",
"경도": "127.039595"
}
]